{"paging":{"pageIndex":1,"pageSize":100,"total":77},"baseComponent":{"id":"AYItUAR_WYP_fvfR51e9","key":"fga-eps-mds_2022-1-schedula-front","name":"2022-1-schedula-front","qualifier":"TRK","measures":[{"metric":"duplicated_lines_density","value":"1.3","bestValue":false},{"metric":"functions","value":"137"},{"metric":"security_rating","value":"1.0","bestValue":true},{"metric":"files","value":"45"},{"metric":"complexity","value":"238"},{"metric":"ncloc","value":"2355"},{"metric":"coverage","value":"51.6","bestValue":false},{"metric":"comment_lines_density","value":"2.3","bestValue":false}]},"components":[{"id":"AYKflDaxDRu3XQ4e5tD1","key":"fga-eps-mds_2022-1-schedula-front:src/pages/categorias/[id]","name":"[id]","qualifier":"DIR","path":"src/pages/categorias/[id]","measures":[{"metric":"duplicated_lines_density","value":"0.0","bestValue":true},{"metric":"functions","value":"10"},{"metric":"security_rating","value":"1.0","bestValue":true},{"metric":"files","value":"1"},{"metric":"complexity","value":"22"},{"metric":"ncloc","value":"173"},{"metric":"comment_lines_density","value":"0.6","bestValue":false}]},{"id":"AYItUKSgstoDJrmV31U1","key":"fga-eps-mds_2022-1-schedula-front:src/pages/_app.tsx","name":"_app.tsx","qualifier":"FIL","path":"src/pages/_app.tsx","language":"ts","measures":[{"metric":"complexity","value":"3"},{"metric":"functions","value":"2"},{"metric":"ncloc","value":"43"},{"metric":"security_rating","value":"1.0","bestValue":true},{"metric":"comment_lines_density","value":"0.0","bestValue":false},{"metric":"files","value":"1"},{"metric":"test_errors","value":"0","bestValue":true},{"metric":"duplicated_lines_density","value":"0.0","bestValue":true},{"metric":"test_failures","value":"0","bestValue":true}]},{"id":"AYI8HBLUAzN_eZq2qV5P","key":"fga-eps-mds_2022-1-schedula-front:src/pages/_document.tsx","name":"_document.tsx","qualifier":"FIL","path":"src/pages/_document.tsx","language":"ts","measures":[{"metric":"complexity","value":"1"},{"metric":"functions","value":"1"},{"metric":"ncloc","value":"27"},{"metric":"security_rating","value":"1.0","bestValue":true},{"metric":"comment_lines_density","value":"0.0","bestValue":false},{"metric":"files","value":"1"},{"metric":"test_errors","value":"0","bestValue":true},{"metric":"duplicated_lines_density","value":"0.0","bestValue":true},{"metric":"test_failures","value":"0","bestValue":true}]},{"id":"AYKflDaxDRu3XQ4e5tD8","key":"fga-eps-mds_2022-1-schedula-front:src/services/api.ts","name":"api.ts","qualifier":"FIL","path":"src/services/api.ts","language":"ts","measures":[{"metric":"complexity","value":"9"},{"metric":"functions","value":"5"},{"metric":"ncloc","value":"52"},{"metric":"security_rating","value":"1.0","bestValue":true},{"metric":"comment_lines_density","value":"1.9","bestValue":false},{"metric":"files","value":"1"},{"metric":"test_errors","value":"0","bestValue":true},{"metric":"duplicated_lines_density","value":"0.0","bestValue":true},{"metric":"test_failures","value":"0","bestValue":true}]},{"id":"AYKflDaxDRu3XQ4e5tD5","key":"fga-eps-mds_2022-1-schedula-front:src/styles/Button.ts","name":"Button.ts","qualifier":"FIL","path":"src/styles/Button.ts","language":"ts","measures":[{"metric":"complexity","value":"0"},{"metric":"functions","value":"0"},{"metric":"ncloc","value":"29"},{"metric":"security_rating","value":"1.0","bestValue":true},{"metric":"comment_lines_density","value":"19.4","bestValue":false},{"metric":"files","value":"1"},{"metric":"test_errors","value":"0","bestValue":true},{"metric":"duplicated_lines_density","value":"0.0","bestValue":true},{"metric":"test_failures","value":"0","bestValue":true}]},{"id":"AYKflDaxDRu3XQ4e5tEJ","key":"fga-eps-mds_2022-1-schedula-front:src/components/Forms/CategoriaForm","name":"CategoriaForm","qualifier":"DIR","path":"src/components/Forms/CategoriaForm","measures":[{"metric":"duplicated_lines_density","value":"26.1","bestValue":false},{"metric":"functions","value":"1"},{"metric":"security_rating","value":"1.0","bestValue":true},{"metric":"files","value":"1"},{"metric":"complexity","value":"3"},{"metric":"ncloc","value":"65"},{"metric":"coverage","value":"0.0","bestValue":false},{"metric":"comment_lines_density","value":"0.0","bestValue":false}]},{"id":"AYKflDaxDRu3XQ4e5tD2","key":"fga-eps-mds_2022-1-schedula-front:src/pages/categorias","name":"categorias","qualifier":"DIR","path":"src/pages/categorias","measures":[{"metric":"duplicated_lines_density","value":"0.0","bestValue":true},{"metric":"functions","value":"22"},{"metric":"security_rating","value":"1.0","bestValue":true},{"metric":"files","value":"2"},{"metric":"complexity","value":"44"},{"metric":"ncloc","value":"319"},{"metric":"comment_lines_density","value":"0.3","bestValue":false}]},{"id":"AYK8qKJrE526gXJ5FZrl","key":"fga-eps-mds_2022-1-schedula-front:src/components/Forms/CidadeForm","name":"CidadeForm","qualifier":"DIR","path":"src/components/Forms/CidadeForm","measures":[{"metric":"duplicated_lines_density","value":"36.0","bestValue":false},{"metric":"functions","value":"1"},{"metric":"security_rating","value":"1.0","bestValue":true},{"metric":"files","value":"1"},{"metric":"complexity","value":"2"},{"metric":"ncloc","value":"46"},{"metric":"coverage","value":"0.0","bestValue":false},{"metric":"comment_lines_density","value":"0.0","bestValue":false}]},{"id":"AYK8qKJrE526gXJ5FZrh","key":"fga-eps-mds_2022-1-schedula-front:src/pages/cidades","name":"cidades","qualifier":"DIR","path":"src/pages/cidades","measures":[{"metric":"duplicated_lines_density","value":"0.0","bestValue":true},{"metric":"functions","value":"10"},{"metric":"security_rating","value":"1.0","bestValue":true},{"metric":"files","value":"1"},{"metric":"complexity","value":"20"},{"metric":"ncloc","value":"127"},{"metric":"comment_lines_density","value":"0.0","bestValue":false}]},{"id":"AYK8qKJrE526gXJ5FZrj","key":"fga-eps-mds_2022-1-schedula-front:src/services/Cidades","name":"Cidades","qualifier":"DIR","path":"src/services/Cidades","measures":[{"metric":"duplicated_lines_density","value":"0.0","bestValue":true},{"metric":"functions","value":"3"},{"metric":"security_rating","value":"1.0","bestValue":true},{"metric":"files","value":"1"},{"metric":"complexity","value":"3"},{"metric":"ncloc","value":"22"},{"metric":"comment_lines_density","value":"0.0","bestValue":false}]},{"id":"AYIxQn1jlxVd-YOFw93N","key":"fga-eps-mds_2022-1-schedula-front:src/components","name":"components","qualifier":"DIR","path":"src/components","measures":[{"metric":"duplicated_lines_density","value":"3.0","bestValue":false},{"metric":"functions","value":"47"},{"metric":"security_rating","value":"1.0","bestValue":true},{"metric":"files","value":"19"},{"metric":"complexity","value":"79"},{"metric":"ncloc","value":"1076"},{"metric":"coverage","value":"60.8","bestValue":false},{"metric":"comment_lines_density","value":"0.2","bestValue":false}]},{"id":"AYIxQn1jlxVd-YOFw93Q","key":"fga-eps-mds_2022-1-schedula-front:src/layout/DefaultLayout.tsx","name":"DefaultLayout.tsx","qualifier":"FIL","path":"src/layout/DefaultLayout.tsx","language":"ts","measures":[{"metric":"complexity","value":"1"},{"metric":"functions","value":"1"},{"metric":"ncloc","value":"27"},{"metric":"coverage","value":"0.0","bestValue":false},{"metric":"security_rating","value":"1.0","bestValue":true},{"metric":"comment_lines_density","value":"0.0","bestValue":false},{"metric":"files","value":"1"},{"metric":"test_errors","value":"0","bestValue":true},{"metric":"duplicated_lines_density","value":"0.0","bestValue":true},{"metric":"test_failures","value":"0","bestValue":true}]},{"id":"AYKflDaxDRu3XQ4e5tD7","key":"fga-eps-mds_2022-1-schedula-front:src/services/DetalhadorChamados","name":"DetalhadorChamados","qualifier":"DIR","path":"src/services/DetalhadorChamados","measures":[{"metric":"duplicated_lines_density","value":"0.0","bestValue":true},{"metric":"functions","value":"3"},{"metric":"security_rating","value":"1.0","bestValue":true},{"metric":"files","value":"1"},{"metric":"complexity","value":"3"},{"metric":"ncloc","value":"23"},{"metric":"comment_lines_density","value":"0.0","bestValue":false}]},{"id":"AYLD-s4R3x8FAgsCTvj_","key":"fga-eps-mds_2022-1-schedula-front:src/components/Footnote","name":"Footnote","qualifier":"DIR","path":"src/components/Footnote","measures":[{"metric":"duplicated_lines_density","value":"0.0","bestValue":true},{"metric":"functions","value":"2"},{"metric":"security_rating","value":"1.0","bestValue":true},{"metric":"files","value":"2"},{"metric":"complexity","value":"10"},{"metric":"ncloc","value":"168"},{"metric":"coverage","value":"0.0","bestValue":false},{"metric":"comment_lines_density","value":"0.0","bestValue":false}]},{"id":"AYKflDaxDRu3XQ4e5tEM","key":"fga-eps-mds_2022-1-schedula-front:src/components/Forms","name":"Forms","qualifier":"DIR","path":"src/components/Forms","measures":[{"metric":"duplicated_lines_density","value":"10.3","bestValue":false},{"metric":"functions","value":"6"},{"metric":"security_rating","value":"1.0","bestValue":true},{"metric":"files","value":"4"},{"metric":"complexity","value":"23"},{"metric":"ncloc","value":"334"},{"metric":"coverage","value":"0.0","bestValue":false},{"metric":"comment_lines_density","value":"0.0","bestValue":false}]},{"id":"AYKflDaxDRu3XQ4e5tEO","key":"fga-eps-mds_2022-1-schedula-front:src/hooks","name":"hooks","qualifier":"DIR","path":"src/hooks","measures":[{"metric":"duplicated_lines_density","value":"0.0","bestValue":true},{"metric":"functions","value":"2"},{"metric":"security_rating","value":"1.0","bestValue":true},{"metric":"files","value":"1"},{"metric":"complexity","value":"7"},{"metric":"ncloc","value":"63"},{"metric":"coverage","value":"0.0","bestValue":false},{"metric":"comment_lines_density","value":"6.0","bestValue":false}]},{"id":"AYK8qKJrE526gXJ5FZri","key":"fga-eps-mds_2022-1-schedula-front:src/services/Cidades/index.ts","name":"index.ts","qualifier":"FIL","path":"src/services/Cidades/index.ts","language":"ts","measures":[{"metric":"complexity","value":"3"},{"metric":"functions","value":"3"},{"metric":"ncloc","value":"22"},{"metric":"security_rating","value":"1.0","bestValue":true},{"metric":"comment_lines_density","value":"0.0","bestValue":false},{"metric":"files","value":"1"},{"metric":"test_errors","value":"0","bestValue":true},{"metric":"duplicated_lines_density","value":"0.0","bestValue":true},{"metric":"test_failures","value":"0","bestValue":true}]},{"id":"AYKflDaxDRu3XQ4e5tD6","key":"fga-eps-mds_2022-1-schedula-front:src/services/DetalhadorChamados/index.ts","name":"index.ts","qualifier":"FIL","path":"src/services/DetalhadorChamados/index.ts","language":"ts","measures":[{"metric":"complexity","value":"3"},{"metric":"functions","value":"3"},{"metric":"ncloc","value":"23"},{"metric":"security_rating","value":"1.0","bestValue":true},{"metric":"comment_lines_density","value":"0.0","bestValue":false},{"metric":"files","value":"1"},{"metric":"test_errors","value":"0","bestValue":true},{"metric":"duplicated_lines_density","value":"0.0","bestValue":true},{"metric":"test_failures","value":"0","bestValue":true}]},{"id":"AYKflDaxDRu3XQ4e5tD-","key":"fga-eps-mds_2022-1-schedula-front:src/services/Problemas/index.ts","name":"index.ts","qualifier":"FIL","path":"src/services/Problemas/index.ts","language":"ts","measures":[{"metric":"complexity","value":"3"},{"metric":"functions","value":"3"},{"metric":"ncloc","value":"18"},{"metric":"security_rating","value":"1.0","bestValue":true},{"metric":"comment_lines_density","value":"0.0","bestValue":false},{"metric":"files","value":"1"},{"metric":"test_errors","value":"0","bestValue":true},{"metric":"duplicated_lines_density","value":"0.0","bestValue":true},{"metric":"test_failures","value":"0","bestValue":true}]},{"id":"AYKflDaxDRu3XQ4e5tEA","key":"fga-eps-mds_2022-1-schedula-front:src/services/Usuarios/index.ts","name":"index.ts","qualifier":"FIL","path":"src/services/Usuarios/index.ts","language":"ts","measures":[{"metric":"complexity","value":"2"},{"metric":"functions","value":"2"},{"metric":"ncloc","value":"18"},{"metric":"security_rating","value":"1.0","bestValue":true},{"metric":"comment_lines_density","value":"0.0","bestValue":false},{"metric":"files","value":"1"},{"metric":"test_errors","value":"0","bestValue":true},{"metric":"duplicated_lines_density","value":"0.0","bestValue":true},{"metric":"test_failures","value":"0","bestValue":true}]},{"id":"AYLAkZKyNcmwacoIScTZ","key":"fga-eps-mds_2022-1-schedula-front:src/services/Workstation/index.ts","name":"index.ts","qualifier":"FIL","path":"src/services/Workstation/index.ts","language":"ts","measures":[{"metric":"complexity","value":"2"},{"metric":"functions","value":"2"},{"metric":"ncloc","value":"18"},{"metric":"security_rating","value":"1.0","bestValue":true},{"metric":"comment_lines_density","value":"0.0","bestValue":false},{"metric":"files","value":"1"},{"metric":"test_errors","value":"0","bestValue":true},{"metric":"duplicated_lines_density","value":"0.0","bestValue":true},{"metric":"test_failures","value":"0","bestValue":true}]},{"id":"AYItUKSgstoDJrmV31U0","key":"fga-eps-mds_2022-1-schedula-front:src/pages/index.tsx","name":"index.tsx","qualifier":"FIL","path":"src/pages/index.tsx","language":"ts","measures":[{"metric":"complexity","value":"2"},{"metric":"functions","value":"2"},{"metric":"ncloc","value":"8"},{"metric":"security_rating","value":"1.0","bestValue":true},{"metric":"comment_lines_density","value":"0.0","bestValue":false},{"metric":"files","value":"1"},{"metric":"test_errors","value":"0","bestValue":true},{"metric":"duplicated_lines_density","value":"0.0","bestValue":true},{"metric":"test_failures","value":"0","bestValue":true}]},{"id":"AYK8qKJrE526gXJ5FZrg","key":"fga-eps-mds_2022-1-schedula-front:src/pages/cidades/index.tsx","name":"index.tsx","qualifier":"FIL","path":"src/pages/cidades/index.tsx","language":"ts","measures":[{"metric":"complexity","value":"20"},{"metric":"functions","value":"10"},{"metric":"ncloc","value":"127"},{"metric":"security_rating","value":"1.0","bestValue":true},{"metric":"comment_lines_density","value":"0.0","bestValue":false},{"metric":"files","value":"1"},{"metric":"test_errors","value":"0","bestValue":true},{"metric":"duplicated_lines_density","value":"0.0","bestValue":true},{"metric":"test_failures","value":"0","bestValue":true}]},{"id":"AYKflDaxDRu3XQ4e5tDz","key":"fga-eps-mds_2022-1-schedula-front:src/pages/categorias/index.tsx","name":"index.tsx","qualifier":"FIL","path":"src/pages/categorias/index.tsx","language":"ts","measures":[{"metric":"complexity","value":"22"},{"metric":"functions","value":"12"},{"metric":"ncloc","value":"146"},{"metric":"security_rating","value":"1.0","bestValue":true},{"metric":"comment_lines_density","value":"0.0","bestValue":false},{"metric":"files","value":"1"},{"metric":"test_errors","value":"0","bestValue":true},{"metric":"duplicated_lines_density","value":"0.0","bestValue":true},{"metric":"test_failures","value":"0","bestValue":true}]},{"id":"AYKflDaxDRu3XQ4e5tD3","key":"fga-eps-mds_2022-1-schedula-front:src/pages/usuarios/index.tsx","name":"index.tsx","qualifier":"FIL","path":"src/pages/usuarios/index.tsx","language":"ts","measures":[{"metric":"complexity","value":"25"},{"metric":"functions","value":"11"},{"metric":"ncloc","value":"159"},{"metric":"security_rating","value":"1.0","bestValue":true},{"metric":"comment_lines_density","value":"0.0","bestValue":false},{"metric":"files","value":"1"},{"metric":"test_errors","value":"0","bestValue":true},{"metric":"duplicated_lines_density","value":"0.0","bestValue":true},{"metric":"test_failures","value":"0","bestValue":true}]},{"id":"AYLAkZKyNcmwacoIScTX","key":"fga-eps-mds_2022-1-schedula-front:src/pages/workstation/index.tsx","name":"index.tsx","qualifier":"FIL","path":"src/pages/workstation/index.tsx","language":"ts","measures":[{"metric":"complexity","value":"20"},{"metric":"functions","value":"10"},{"metric":"ncloc","value":"147"},{"metric":"security_rating","value":"1.0","bestValue":true},{"metric":"comment_lines_density","value":"0.0","bestValue":false},{"metric":"files","value":"1"},{"metric":"test_errors","value":"0","bestValue":true},{"metric":"duplicated_lines_density","value":"0.0","bestValue":true},{"metric":"test_failures","value":"0","bestValue":true}]},{"id":"AYJtsWcdBfdiaV3E-1xQ","key":"fga-eps-mds_2022-1-schedula-front:src/components/SideBar/index.tsx","name":"index.tsx","qualifier":"FIL","path":"src/components/SideBar/index.tsx","language":"ts","measures":[{"metric":"complexity","value":"2"},{"metric":"functions","value":"2"},{"metric":"ncloc","value":"40"},{"metric":"coverage","value":"100.0","bestValue":true},{"metric":"security_rating","value":"1.0","bestValue":true},{"metric":"comment_lines_density","value":"2.4","bestValue":false},{"metric":"files","value":"1"},{"metric":"test_errors","value":"0","bestValue":true},{"metric":"duplicated_lines_density","value":"0.0","bestValue":true},{"metric":"test_failures","value":"0","bestValue":true}]},{"id":"AYKflDaxDRu3XQ4e5tEF","key":"fga-eps-mds_2022-1-schedula-front:src/components/ListItem/index.tsx","name":"index.tsx","qualifier":"FIL","path":"src/components/ListItem/index.tsx","language":"ts","measures":[{"metric":"complexity","value":"1"},{"metric":"functions","value":"1"},{"metric":"ncloc","value":"42"},{"metric":"coverage","value":"100.0","bestValue":true},{"metric":"security_rating","value":"1.0","bestValue":true},{"metric":"comment_lines_density","value":"0.0","bestValue":false},{"metric":"files","value":"1"},{"metric":"test_errors","value":"0","bestValue":true},{"metric":"duplicated_lines_density","value":"0.0","bestValue":true},{"metric":"test_failures","value":"0","bestValue":true}]},{"id":"AYLCiAJF-22VU8XA4Kx9","key":"fga-eps-mds_2022-1-schedula-front:src/components/ListItem/ListItemActions/index.tsx","name":"index.tsx","qualifier":"FIL","path":"src/components/ListItem/ListItemActions/index.tsx","language":"ts","measures":[{"metric":"complexity","value":"4"},{"metric":"functions","value":"3"},{"metric":"ncloc","value":"129"},{"metric":"coverage","value":"100.0","bestValue":true},{"metric":"security_rating","value":"1.0","bestValue":true},{"metric":"comment_lines_density","value":"0.0","bestValue":false},{"metric":"files","value":"1"},{"metric":"test_errors","value":"0","bestValue":true},{"metric":"duplicated_lines_density","value":"0.0","bestValue":true},{"metric":"test_failures","value":"0","bestValue":true}]},{"id":"AYK8qKJrE526gXJ5FZrk","key":"fga-eps-mds_2022-1-schedula-front:src/components/Forms/CidadeForm/index.tsx","name":"index.tsx","qualifier":"FIL","path":"src/components/Forms/CidadeForm/index.tsx","language":"ts","measures":[{"metric":"files","value":"1"},{"metric":"ncloc","value":"46"},{"metric":"coverage","value":"0.0","bestValue":false},{"metric":"functions","value":"1"},{"metric":"complexity","value":"2"},{"metric":"security_rating","value":"1.0","bestValue":true},{"metric":"comment_lines_density","value":"0.0","bestValue":false},{"metric":"duplicated_lines_density","value":"36.0","bestValue":false},{"metric":"test_errors","value":"0","bestValue":true},{"metric":"test_failures","value":"0","bestValue":true}]},{"id":"AYKflDaxDRu3XQ4e5tEI","key":"fga-eps-mds_2022-1-schedula-front:src/components/Forms/CategoriaForm/index.tsx","name":"index.tsx","qualifier":"FIL","path":"src/components/Forms/CategoriaForm/index.tsx","language":"ts","measures":[{"metric":"files","value":"1"},{"metric":"ncloc","value":"65"},{"metric":"coverage","value":"0.0","bestValue":false},{"metric":"functions","value":"1"},{"metric":"complexity","value":"3"},{"metric":"security_rating","value":"1.0","bestValue":true},{"metric":"comment_lines_density","value":"0.0","bestValue":false},{"metric":"duplicated_lines_density","value":"26.1","bestValue":false},{"metric":"test_errors","value":"0","bestValue":true},{"metric":"test_failures","value":"0","bestValue":true}]},{"id":"AYKflDaxDRu3XQ4e5tEK","key":"fga-eps-mds_2022-1-schedula-front:src/components/Forms/UserForm/index.tsx","name":"index.tsx","qualifier":"FIL","path":"src/components/Forms/UserForm/index.tsx","language":"ts","measures":[{"metric":"complexity","value":"15"},{"metric":"functions","value":"3"},{"metric":"ncloc","value":"162"},{"metric":"coverage","value":"0.0","bestValue":false},{"metric":"security_rating","value":"1.0","bestValue":true},{"metric":"comment_lines_density","value":"0.0","bestValue":false},{"metric":"files","value":"1"},{"metric":"test_errors","value":"0","bestValue":true},{"metric":"duplicated_lines_density","value":"0.0","bestValue":true},{"metric":"test_failures","value":"0","bestValue":true}]},{"id":"AYLAkZKyNcmwacoIScTV","key":"fga-eps-mds_2022-1-schedula-front:src/components/Forms/WorkstationForm/index.tsx","name":"index.tsx","qualifier":"FIL","path":"src/components/Forms/WorkstationForm/index.tsx","language":"ts","measures":[{"metric":"complexity","value":"3"},{"metric":"functions","value":"1"},{"metric":"ncloc","value":"61"},{"metric":"coverage","value":"0.0","bestValue":false},{"metric":"security_rating","value":"1.0","bestValue":true},{"metric":"comment_lines_density","value":"0.0","bestValue":false},{"metric":"files","value":"1"},{"metric":"test_errors","value":"0","bestValue":true},{"metric":"duplicated_lines_density","value":"0.0","bestValue":true},{"metric":"test_failures","value":"0","bestValue":true}]},{"id":"AYKnBE2CUSu0TQjk7dcW","key":"fga-eps-mds_2022-1-schedula-front:src/components/RefreshButton/index.tsx","name":"index.tsx","qualifier":"FIL","path":"src/components/RefreshButton/index.tsx","language":"ts","measures":[{"metric":"complexity","value":"3"},{"metric":"functions","value":"3"},{"metric":"ncloc","value":"31"},{"metric":"coverage","value":"0.0","bestValue":false},{"metric":"security_rating","value":"1.0","bestValue":true},{"metric":"comment_lines_density","value":"0.0","bestValue":false},{"metric":"files","value":"1"},{"metric":"test_errors","value":"0","bestValue":true},{"metric":"duplicated_lines_density","value":"0.0","bestValue":true},{"metric":"test_failures","value":"0","bestValue":true}]},{"id":"AYLC0lSLrsYRDLSdmF_-","key":"fga-eps-mds_2022-1-schedula-front:src/components/List/index.tsx","name":"index.tsx","qualifier":"FIL","path":"src/components/List/index.tsx","language":"ts","measures":[{"metric":"complexity","value":"2"},{"metric":"functions","value":"1"},{"metric":"ncloc","value":"19"},{"metric":"coverage","value":"100.0","bestValue":true},{"metric":"security_rating","value":"1.0","bestValue":true},{"metric":"comment_lines_density","value":"0.0","bestValue":false},{"metric":"files","value":"1"},{"metric":"test_errors","value":"0","bestValue":true},{"metric":"duplicated_lines_density","value":"0.0","bestValue":true},{"metric":"test_failures","value":"0","bestValue":true}]},{"id":"AYLD-s4R3x8FAgsCTvj9","key":"fga-eps-mds_2022-1-schedula-front:src/components/Footnote/index.tsx","name":"index.tsx","qualifier":"FIL","path":"src/components/Footnote/index.tsx","language":"ts","measures":[{"metric":"complexity","value":"3"},{"metric":"functions","value":"1"},{"metric":"ncloc","value":"67"},{"metric":"coverage","value":"0.0","bestValue":false},{"metric":"security_rating","value":"1.0","bestValue":true},{"metric":"comment_lines_density","value":"0.0","bestValue":false},{"metric":"files","value":"1"},{"metric":"test_errors","value":"0","bestValue":true},{"metric":"duplicated_lines_density","value":"0.0","bestValue":true},{"metric":"test_failures","value":"0","bestValue":true}]},{"id":"AYKJKCjH2ykrS2Aqr75h","key":"fga-eps-mds_2022-1-schedula-front:src/routes/index.tsx","name":"index.tsx","qualifier":"FIL","path":"src/routes/index.tsx","language":"ts","measures":[{"metric":"complexity","value":"0"},{"metric":"functions","value":"0"},{"metric":"ncloc","value":"26"},{"metric":"coverage","value":"100.0","bestValue":true},{"metric":"security_rating","value":"1.0","bestValue":true},{"metric":"comment_lines_density","value":"43.5","bestValue":false},{"metric":"files","value":"1"},{"metric":"test_errors","value":"0","bestValue":true},{"metric":"duplicated_lines_density","value":"0.0","bestValue":true},{"metric":"test_failures","value":"0","bestValue":true}]},{"id":"AYItsuWexNkFlxCgUkYF","key":"fga-eps-mds_2022-1-schedula-front:jest.config.js","name":"jest.config.js","qualifier":"FIL","path":"jest.config.js","language":"js","measures":[{"metric":"complexity","value":"0"},{"metric":"functions","value":"0"},{"metric":"ncloc","value":"30"},{"metric":"security_rating","value":"1.0","bestValue":true},{"metric":"comment_lines_density","value":"18.9","bestValue":false},{"metric":"files","value":"1"},{"metric":"test_errors","value":"0","bestValue":true},{"metric":"duplicated_lines_density","value":"0.0","bestValue":true},{"metric":"test_failures","value":"0","bestValue":true}]},{"id":"AYItsuWexNkFlxCgUkYE","key":"fga-eps-mds_2022-1-schedula-front:jest.setup.js","name":"jest.setup.js","qualifier":"FIL","path":"jest.setup.js","language":"js","measures":[{"metric":"complexity","value":"0"},{"metric":"functions","value":"0"},{"metric":"ncloc","value":"2"},{"metric":"security_rating","value":"1.0","bestValue":true},{"metric":"comment_lines_density","value":"0.0","bestValue":false},{"metric":"files","value":"1"},{"metric":"test_errors","value":"0","bestValue":true},{"metric":"duplicated_lines_density","value":"0.0","bestValue":true},{"metric":"test_failures","value":"0","bestValue":true}]},{"id":"AYIxQn1jlxVd-YOFw93R","key":"fga-eps-mds_2022-1-schedula-front:src/layout","name":"layout","qualifier":"DIR","path":"src/layout","measures":[{"metric":"duplicated_lines_density","value":"0.0","bestValue":true},{"metric":"functions","value":"1"},{"metric":"security_rating","value":"1.0","bestValue":true},{"metric":"files","value":"1"},{"metric":"complexity","value":"1"},{"metric":"ncloc","value":"27"},{"metric":"coverage","value":"0.0","bestValue":false},{"metric":"comment_lines_density","value":"0.0","bestValue":false}]},{"id":"AYLC0lSLrsYRDLSdmF__","key":"fga-eps-mds_2022-1-schedula-front:src/components/List","name":"List","qualifier":"DIR","path":"src/components/List","measures":[{"metric":"duplicated_lines_density","value":"0.0","bestValue":true},{"metric":"functions","value":"5"},{"metric":"security_rating","value":"1.0","bestValue":true},{"metric":"files","value":"2"},{"metric":"complexity","value":"6"},{"metric":"ncloc","value":"56"},{"metric":"coverage","value":"100.0","bestValue":true},{"metric":"comment_lines_density","value":"0.0","bestValue":false}]},{"id":"AYLC5Lro7pR__-6PuOP0","key":"fga-eps-mds_2022-1-schedula-front:src/components/List/List.spec.tsx","name":"List.spec.tsx","qualifier":"FIL","path":"src/components/List/List.spec.tsx","language":"ts","measures":[{"metric":"complexity","value":"4"},{"metric":"functions","value":"4"},{"metric":"ncloc","value":"37"},{"metric":"security_rating","value":"1.0","bestValue":true},{"metric":"comment_lines_density","value":"0.0","bestValue":false},{"metric":"files","value":"1"},{"metric":"test_errors","value":"0","bestValue":true},{"metric":"duplicated_lines_density","value":"0.0","bestValue":true},{"metric":"test_failures","value":"0","bestValue":true}]},{"id":"AYKflDaxDRu3XQ4e5tEH","key":"fga-eps-mds_2022-1-schedula-front:src/components/ListItem","name":"ListItem","qualifier":"DIR","path":"src/components/ListItem","measures":[{"metric":"duplicated_lines_density","value":"0.0","bestValue":true},{"metric":"functions","value":"18"},{"metric":"security_rating","value":"1.0","bestValue":true},{"metric":"files","value":"5"},{"metric":"complexity","value":"19"},{"metric":"ncloc","value":"311"},{"metric":"coverage","value":"100.0","bestValue":true},{"metric":"comment_lines_density","value":"0.0","bestValue":false}]},{"id":"AYLCiAJF-22VU8XA4KyA","key":"fga-eps-mds_2022-1-schedula-front:src/components/ListItem/ListItem.spec.tsx","name":"ListItem.spec.tsx","qualifier":"FIL","path":"src/components/ListItem/ListItem.spec.tsx","language":"ts","measures":[{"metric":"complexity","value":"6"},{"metric":"functions","value":"6"},{"metric":"ncloc","value":"35"},{"metric":"security_rating","value":"1.0","bestValue":true},{"metric":"comment_lines_density","value":"0.0","bestValue":false},{"metric":"files","value":"1"},{"metric":"test_errors","value":"0","bestValue":true},{"metric":"duplicated_lines_density","value":"0.0","bestValue":true},{"metric":"test_failures","value":"0","bestValue":true}]},{"id":"AYLCiAJF-22VU8XA4Kx_","key":"fga-eps-mds_2022-1-schedula-front:src/components/ListItem/ListItemActions","name":"ListItemActions","qualifier":"DIR","path":"src/components/ListItem/ListItemActions","measures":[{"metric":"duplicated_lines_density","value":"0.0","bestValue":true},{"metric":"functions","value":"9"},{"metric":"security_rating","value":"1.0","bestValue":true},{"metric":"files","value":"2"},{"metric":"complexity","value":"10"},{"metric":"ncloc","value":"199"},{"metric":"coverage","value":"100.0","bestValue":true},{"metric":"comment_lines_density","value":"0.0","bestValue":false}]},{"id":"AYLCiAJF-22VU8XA4Kx-","key":"fga-eps-mds_2022-1-schedula-front:src/components/ListItem/ListItemActions/ListItemActions.spec.tsx","name":"ListItemActions.spec.tsx","qualifier":"FIL","path":"src/components/ListItem/ListItemActions/ListItemActions.spec.tsx","language":"ts","measures":[{"metric":"complexity","value":"6"},{"metric":"functions","value":"6"},{"metric":"ncloc","value":"70"},{"metric":"security_rating","value":"1.0","bestValue":true},{"metric":"comment_lines_density","value":"0.0","bestValue":false},{"metric":"files","value":"1"},{"metric":"test_errors","value":"0","bestValue":true},{"metric":"duplicated_lines_density","value":"0.0","bestValue":true},{"metric":"test_failures","value":"0","bestValue":true}]},{"id":"AYKflDaxDRu3XQ4e5tEG","key":"fga-eps-mds_2022-1-schedula-front:src/components/ListItem/LIstItemSkeleton.tsx","name":"LIstItemSkeleton.tsx","qualifier":"FIL","path":"src/components/ListItem/LIstItemSkeleton.tsx","language":"ts","measures":[{"metric":"complexity","value":"2"},{"metric":"functions","value":"2"},{"metric":"ncloc","value":"35"},{"metric":"coverage","value":"100.0","bestValue":true},{"metric":"security_rating","value":"1.0","bestValue":true},{"metric":"comment_lines_density","value":"0.0","bestValue":false},{"metric":"files","value":"1"},{"metric":"test_errors","value":"0","bestValue":true},{"metric":"duplicated_lines_density","value":"0.0","bestValue":true},{"metric":"test_failures","value":"0","bestValue":true}]},{"id":"AYLIOyDOUsM8e7WIVtUV","key":"fga-eps-mds_2022-1-schedula-front:metrics","name":"metrics","qualifier":"DIR","path":"metrics","measures":[{"metric":"duplicated_lines_density","value":"0.0","bestValue":true},{"metric":"functions","value":"5"},{"metric":"security_rating","value":"1.0","bestValue":true},{"metric":"files","value":"1"},{"metric":"complexity","value":"6"},{"metric":"ncloc","value":"46"},{"metric":"coverage","value":"0.0","bestValue":false},{"metric":"comment_lines_density","value":"0.0","bestValue":false}]},{"id":"AYKflDaxDRu3XQ4e5tED","key":"fga-eps-mds_2022-1-schedula-front:src/components/Modal","name":"Modal","qualifier":"DIR","path":"src/components/Modal","measures":[{"metric":"duplicated_lines_density","value":"0.0","bestValue":true},{"metric":"functions","value":"1"},{"metric":"security_rating","value":"1.0","bestValue":true},{"metric":"files","value":"1"},{"metric":"complexity","value":"1"},{"metric":"ncloc","value":"25"},{"metric":"coverage","value":"0.0","bestValue":false},{"metric":"comment_lines_density","value":"0.0","bestValue":false}]},{"id":"AYKflDaxDRu3XQ4e5tEC","key":"fga-eps-mds_2022-1-schedula-front:src/components/Modal/Modal.tsx","name":"Modal.tsx","qualifier":"FIL","path":"src/components/Modal/Modal.tsx","language":"ts","measures":[{"metric":"complexity","value":"1"},{"metric":"functions","value":"1"},{"metric":"ncloc","value":"25"},{"metric":"coverage","value":"0.0","bestValue":false},{"metric":"security_rating","value":"1.0","bestValue":true},{"metric":"comment_lines_density","value":"0.0","bestValue":false},{"metric":"files","value":"1"},{"metric":"test_errors","value":"0","bestValue":true},{"metric":"duplicated_lines_density","value":"0.0","bestValue":true},{"metric":"test_failures","value":"0","bestValue":true}]},{"id":"AYItUKSgstoDJrmV31U9","key":"fga-eps-mds_2022-1-schedula-front:next.config.js","name":"next.config.js","qualifier":"FIL","path":"next.config.js","language":"js","measures":[{"metric":"complexity","value":"4"},{"metric":"functions","value":"2"},{"metric":"ncloc","value":"20"},{"metric":"security_rating","value":"1.0","bestValue":true},{"metric":"comment_lines_density","value":"39.4","bestValue":false},{"metric":"files","value":"1"},{"metric":"test_errors","value":"0","bestValue":true},{"metric":"duplicated_lines_density","value":"0.0","bestValue":true},{"metric":"test_failures","value":"0","bestValue":true}]},{"id":"AYItUKSgstoDJrmV31U8","key":"fga-eps-mds_2022-1-schedula-front:package.json","name":"package.json","qualifier":"FIL","path":"package.json","language":"json","measures":[{"metric":"security_rating","value":"1.0","bestValue":true},{"metric":"files","value":"1"},{"metric":"test_errors","value":"0","bestValue":true},{"metric":"duplicated_lines_density","value":"0.0","bestValue":true},{"metric":"test_failures","value":"0","bestValue":true}]},{"id":"AYKflDaxDRu3XQ4e5tEE","key":"fga-eps-mds_2022-1-schedula-front:src/components/PageHeader.tsx","name":"PageHeader.tsx","qualifier":"FIL","path":"src/components/PageHeader.tsx","language":"ts","measures":[{"metric":"complexity","value":"1"},{"metric":"functions","value":"1"},{"metric":"ncloc","value":"18"},{"metric":"coverage","value":"0.0","bestValue":false},{"metric":"security_rating","value":"1.0","bestValue":true},{"metric":"comment_lines_density","value":"0.0","bestValue":false},{"metric":"files","value":"1"},{"metric":"test_errors","value":"0","bestValue":true},{"metric":"duplicated_lines_density","value":"0.0","bestValue":true},{"metric":"test_failures","value":"0","bestValue":true}]},{"id":"AYItUKSgstoDJrmV31U2","key":"fga-eps-mds_2022-1-schedula-front:src/pages","name":"pages","qualifier":"DIR","path":"src/pages","measures":[{"metric":"duplicated_lines_density","value":"0.0","bestValue":true},{"metric":"functions","value":"58"},{"metric":"security_rating","value":"1.0","bestValue":true},{"metric":"files","value":"8"},{"metric":"complexity","value":"115"},{"metric":"ncloc","value":"830"},{"metric":"comment_lines_density","value":"0.1","bestValue":false}]},{"id":"AYKflDaxDRu3XQ4e5tD_","key":"fga-eps-mds_2022-1-schedula-front:src/services/Problemas","name":"Problemas","qualifier":"DIR","path":"src/services/Problemas","measures":[{"metric":"duplicated_lines_density","value":"0.0","bestValue":true},{"metric":"functions","value":"3"},{"metric":"security_rating","value":"1.0","bestValue":true},{"metric":"files","value":"1"},{"metric":"complexity","value":"3"},{"metric":"ncloc","value":"18"},{"metric":"comment_lines_density","value":"0.0","bestValue":false}]},{"id":"AYKflDaxDRu3XQ4e5tD0","key":"fga-eps-mds_2022-1-schedula-front:src/pages/categorias/[id]/problemas.tsx","name":"problemas.tsx","qualifier":"FIL","path":"src/pages/categorias/[id]/problemas.tsx","language":"ts","measures":[{"metric":"complexity","value":"22"},{"metric":"functions","value":"10"},{"metric":"ncloc","value":"173"},{"metric":"security_rating","value":"1.0","bestValue":true},{"metric":"comment_lines_density","value":"0.6","bestValue":false},{"metric":"files","value":"1"},{"metric":"test_errors","value":"0","bestValue":true},{"metric":"duplicated_lines_density","value":"0.0","bestValue":true},{"metric":"test_failures","value":"0","bestValue":true}]},{"id":"AYKnBE2CUSu0TQjk7dcX","key":"fga-eps-mds_2022-1-schedula-front:src/components/RefreshButton","name":"RefreshButton","qualifier":"DIR","path":"src/components/RefreshButton","measures":[{"metric":"duplicated_lines_density","value":"0.0","bestValue":true},{"metric":"functions","value":"3"},{"metric":"security_rating","value":"1.0","bestValue":true},{"metric":"files","value":"1"},{"metric":"complexity","value":"3"},{"metric":"ncloc","value":"31"},{"metric":"coverage","value":"0.0","bestValue":false},{"metric":"comment_lines_density","value":"0.0","bestValue":false}]},{"id":"AYKflDaxDRu3XQ4e5tD9","key":"fga-eps-mds_2022-1-schedula-front:src/services/request.ts","name":"request.ts","qualifier":"FIL","path":"src/services/request.ts","language":"ts","measures":[{"metric":"complexity","value":"4"},{"metric":"functions","value":"4"},{"metric":"ncloc","value":"23"},{"metric":"security_rating","value":"1.0","bestValue":true},{"metric":"comment_lines_density","value":"0.0","bestValue":false},{"metric":"files","value":"1"},{"metric":"test_errors","value":"0","bestValue":true},{"metric":"duplicated_lines_density","value":"0.0","bestValue":true},{"metric":"test_failures","value":"0","bestValue":true}]},{"id":"AYKJKCjH2ykrS2Aqr75i","key":"fga-eps-mds_2022-1-schedula-front:src/routes","name":"routes","qualifier":"DIR","path":"src/routes","measures":[{"metric":"duplicated_lines_density","value":"0.0","bestValue":true},{"metric":"functions","value":"0"},{"metric":"security_rating","value":"1.0","bestValue":true},{"metric":"files","value":"1"},{"metric":"complexity","value":"0"},{"metric":"ncloc","value":"26"},{"metric":"coverage","value":"100.0","bestValue":true},{"metric":"comment_lines_density","value":"43.5","bestValue":false}]},{"id":"AYJtsWcdBfdiaV3E-1xU","key":"fga-eps-mds_2022-1-schedula-front:src/services","name":"services","qualifier":"DIR","path":"src/services","measures":[{"metric":"duplicated_lines_density","value":"0.0","bestValue":true},{"metric":"functions","value":"22"},{"metric":"security_rating","value":"1.0","bestValue":true},{"metric":"files","value":"7"},{"metric":"complexity","value":"26"},{"metric":"ncloc","value":"174"},{"metric":"comment_lines_density","value":"0.6","bestValue":false}]},{"id":"AYLD-s4R3x8FAgsCTvj-","key":"fga-eps-mds_2022-1-schedula-front:src/components/Footnote/ServicesStatus.tsx","name":"ServicesStatus.tsx","qualifier":"FIL","path":"src/components/Footnote/ServicesStatus.tsx","language":"ts","measures":[{"metric":"complexity","value":"7"},{"metric":"functions","value":"1"},{"metric":"ncloc","value":"101"},{"metric":"coverage","value":"0.0","bestValue":false},{"metric":"security_rating","value":"1.0","bestValue":true},{"metric":"comment_lines_density","value":"0.0","bestValue":false},{"metric":"files","value":"1"},{"metric":"test_errors","value":"0","bestValue":true},{"metric":"duplicated_lines_density","value":"0.0","bestValue":true},{"metric":"test_failures","value":"0","bestValue":true}]},{"id":"AYJtsWcdBfdiaV3E-1xR","key":"fga-eps-mds_2022-1-schedula-front:src/components/SideBar","name":"SideBar","qualifier":"DIR","path":"src/components/SideBar","measures":[{"metric":"duplicated_lines_density","value":"0.0","bestValue":true},{"metric":"functions","value":"11"},{"metric":"security_rating","value":"1.0","bestValue":true},{"metric":"files","value":"3"},{"metric":"complexity","value":"16"},{"metric":"ncloc","value":"133"},{"metric":"coverage","value":"87.1","bestValue":false},{"metric":"comment_lines_density","value":"1.5","bestValue":false}]},{"id":"AYKJKCjH2ykrS2Aqr75g","key":"fga-eps-mds_2022-1-schedula-front:src/components/SideBar/Sidebar.spec.tsx","name":"Sidebar.spec.tsx","qualifier":"FIL","path":"src/components/SideBar/Sidebar.spec.tsx","language":"ts","measures":[{"metric":"complexity","value":"8"},{"metric":"functions","value":"7"},{"metric":"ncloc","value":"26"},{"metric":"security_rating","value":"1.0","bestValue":true},{"metric":"comment_lines_density","value":"0.0","bestValue":false},{"metric":"files","value":"1"},{"metric":"test_errors","value":"0","bestValue":true},{"metric":"duplicated_lines_density","value":"0.0","bestValue":true},{"metric":"test_failures","value":"0","bestValue":true}]},{"id":"AYKJKCjH2ykrS2Aqr75f","key":"fga-eps-mds_2022-1-schedula-front:src/components/SideBar/SidebarItem","name":"SidebarItem","qualifier":"DIR","path":"src/components/SideBar/SidebarItem","measures":[{"metric":"duplicated_lines_density","value":"0.0","bestValue":true},{"metric":"functions","value":"2"},{"metric":"security_rating","value":"1.0","bestValue":true},{"metric":"files","value":"1"},{"metric":"complexity","value":"6"},{"metric":"ncloc","value":"67"},{"metric":"coverage","value":"82.6","bestValue":false},{"metric":"comment_lines_density","value":"1.5","bestValue":false}]},{"id":"AYKJKCjH2ykrS2Aqr75e","key":"fga-eps-mds_2022-1-schedula-front:src/components/SideBar/SidebarItem/SideBarItem.tsx","name":"SideBarItem.tsx","qualifier":"FIL","path":"src/components/SideBar/SidebarItem/SideBarItem.tsx","language":"ts","measures":[{"metric":"complexity","value":"6"},{"metric":"functions","value":"2"},{"metric":"ncloc","value":"67"},{"metric":"coverage","value":"82.6","bestValue":false},{"metric":"security_rating","value":"1.0","bestValue":true},{"metric":"comment_lines_density","value":"1.5","bestValue":false},{"metric":"files","value":"1"},{"metric":"test_errors","value":"0","bestValue":true},{"metric":"duplicated_lines_density","value":"0.0","bestValue":true},{"metric":"test_failures","value":"0","bestValue":true}]},{"id":"AYLIOyDOUsM8e7WIVtUU","key":"fga-eps-mds_2022-1-schedula-front:metrics/sonar-metrics.ts","name":"sonar-metrics.ts","qualifier":"FIL","path":"metrics/sonar-metrics.ts","language":"ts","measures":[{"metric":"complexity","value":"6"},{"metric":"functions","value":"5"},{"metric":"ncloc","value":"46"},{"metric":"coverage","value":"0.0","bestValue":false},{"metric":"security_rating","value":"1.0","bestValue":true},{"metric":"comment_lines_density","value":"0.0","bestValue":false},{"metric":"files","value":"1"},{"metric":"test_errors","value":"0","bestValue":true},{"metric":"duplicated_lines_density","value":"0.0","bestValue":true},{"metric":"test_failures","value":"0","bestValue":true}]},{"id":"AYItUKSgstoDJrmV31U6","key":"fga-eps-mds_2022-1-schedula-front:src","name":"src","qualifier":"DIR","path":"src","measures":[{"metric":"duplicated_lines_density","value":"1.4","bestValue":false},{"metric":"functions","value":"130"},{"metric":"security_rating","value":"1.0","bestValue":true},{"metric":"files","value":"39"},{"metric":"complexity","value":"228"},{"metric":"ncloc","value":"2257"},{"metric":"coverage","value":"59.5","bestValue":false},{"metric":"comment_lines_density","value":"1.6","bestValue":false}]},{"id":"AYItUKSgstoDJrmV31U5","key":"fga-eps-mds_2022-1-schedula-front:src/styles","name":"styles","qualifier":"DIR","path":"src/styles","measures":[{"metric":"duplicated_lines_density","value":"0.0","bestValue":true},{"metric":"functions","value":"0"},{"metric":"security_rating","value":"1.0","bestValue":true},{"metric":"files","value":"2"},{"metric":"complexity","value":"0"},{"metric":"ncloc","value":"61"},{"metric":"comment_lines_density","value":"11.6","bestValue":false}]},{"id":"AYKnjjK2g89zSLTDvakC","key":"fga-eps-mds_2022-1-schedula-front:src/styles/Theme.ts","name":"Theme.ts","qualifier":"FIL","path":"src/styles/Theme.ts","language":"ts","measures":[{"metric":"complexity","value":"0"},{"metric":"functions","value":"0"},{"metric":"ncloc","value":"32"},{"metric":"security_rating","value":"1.0","bestValue":true},{"metric":"comment_lines_density","value":"3.0","bestValue":false},{"metric":"files","value":"1"},{"metric":"test_errors","value":"0","bestValue":true},{"metric":"duplicated_lines_density","value":"0.0","bestValue":true},{"metric":"test_failures","value":"0","bestValue":true}]},{"id":"AYItUKSgstoDJrmV31U7","key":"fga-eps-mds_2022-1-schedula-front:tsconfig.json","name":"tsconfig.json","qualifier":"FIL","path":"tsconfig.json","language":"json","measures":[{"metric":"security_rating","value":"1.0","bestValue":true},{"metric":"files","value":"1"},{"metric":"test_errors","value":"0","bestValue":true},{"metric":"duplicated_lines_density","value":"0.0","bestValue":true},{"metric":"test_failures","value":"0","bestValue":true}]},{"id":"AYKflDaxDRu3XQ4e5tEN","key":"fga-eps-mds_2022-1-schedula-front:src/hooks/useRequest.ts","name":"useRequest.ts","qualifier":"FIL","path":"src/hooks/useRequest.ts","language":"ts","measures":[{"metric":"complexity","value":"7"},{"metric":"functions","value":"2"},{"metric":"ncloc","value":"63"},{"metric":"coverage","value":"0.0","bestValue":false},{"metric":"security_rating","value":"1.0","bestValue":true},{"metric":"comment_lines_density","value":"6.0","bestValue":false},{"metric":"files","value":"1"},{"metric":"test_errors","value":"0","bestValue":true},{"metric":"duplicated_lines_density","value":"0.0","bestValue":true},{"metric":"test_failures","value":"0","bestValue":true}]},{"id":"AYKflDaxDRu3XQ4e5tEL","key":"fga-eps-mds_2022-1-schedula-front:src/components/Forms/UserForm","name":"UserForm","qualifier":"DIR","path":"src/components/Forms/UserForm","measures":[{"metric":"duplicated_lines_density","value":"0.0","bestValue":true},{"metric":"functions","value":"3"},{"metric":"security_rating","value":"1.0","bestValue":true},{"metric":"files","value":"1"},{"metric":"complexity","value":"15"},{"metric":"ncloc","value":"162"},{"metric":"coverage","value":"0.0","bestValue":false},{"metric":"comment_lines_density","value":"0.0","bestValue":false}]},{"id":"AYKflDaxDRu3XQ4e5tD4","key":"fga-eps-mds_2022-1-schedula-front:src/pages/usuarios","name":"usuarios","qualifier":"DIR","path":"src/pages/usuarios","measures":[{"metric":"duplicated_lines_density","value":"0.0","bestValue":true},{"metric":"functions","value":"11"},{"metric":"security_rating","value":"1.0","bestValue":true},{"metric":"files","value":"1"},{"metric":"complexity","value":"25"},{"metric":"ncloc","value":"159"},{"metric":"comment_lines_density","value":"0.0","bestValue":false}]},{"id":"AYKflDaxDRu3XQ4e5tEB","key":"fga-eps-mds_2022-1-schedula-front:src/services/Usuarios","name":"Usuarios","qualifier":"DIR","path":"src/services/Usuarios","measures":[{"metric":"duplicated_lines_density","value":"0.0","bestValue":true},{"metric":"functions","value":"2"},{"metric":"security_rating","value":"1.0","bestValue":true},{"metric":"files","value":"1"},{"metric":"complexity","value":"2"},{"metric":"ncloc","value":"18"},{"metric":"comment_lines_density","value":"0.0","bestValue":false}]},{"id":"AYLAkZKyNcmwacoIScTY","key":"fga-eps-mds_2022-1-schedula-front:src/pages/workstation","name":"workstation","qualifier":"DIR","path":"src/pages/workstation","measures":[{"metric":"duplicated_lines_density","value":"0.0","bestValue":true},{"metric":"functions","value":"10"},{"metric":"security_rating","value":"1.0","bestValue":true},{"metric":"files","value":"1"},{"metric":"complexity","value":"20"},{"metric":"ncloc","value":"147"},{"metric":"comment_lines_density","value":"0.0","bestValue":false}]},{"id":"AYLAkZKyNcmwacoIScTa","key":"fga-eps-mds_2022-1-schedula-front:src/services/Workstation","name":"Workstation","qualifier":"DIR","path":"src/services/Workstation","measures":[{"metric":"duplicated_lines_density","value":"0.0","bestValue":true},{"metric":"functions","value":"2"},{"metric":"security_rating","value":"1.0","bestValue":true},{"metric":"files","value":"1"},{"metric":"complexity","value":"2"},{"metric":"ncloc","value":"18"},{"metric":"comment_lines_density","value":"0.0","bestValue":false}]},{"id":"AYLAkZKyNcmwacoIScTW","key":"fga-eps-mds_2022-1-schedula-front:src/components/Forms/WorkstationForm","name":"WorkstationForm","qualifier":"DIR","path":"src/components/Forms/WorkstationForm","measures":[{"metric":"duplicated_lines_density","value":"0.0","bestValue":true},{"metric":"functions","value":"1"},{"metric":"security_rating","value":"1.0","bestValue":true},{"metric":"files","value":"1"},{"metric":"complexity","value":"3"},{"metric":"ncloc","value":"61"},{"metric":"coverage","value":"0.0","bestValue":false},{"metric":"comment_lines_density","value":"0.0","bestValue":false}]}]}